odoo9_addon_stock_picking_sale_order_link-9.0.1.0.0-py2.7-nspkg.pth
odoo9_addon_stock_picking_sale_order_link-9.0.1.0.0.dist-info/top_level.txt
odoo9_addon_stock_picking_sale_order_link-9.0.1.0.0.dist-info/WHEEL
odoo9_addon_stock_picking_sale_order_link-9.0.1.0.0.dist-info/RECORD
odoo9_addon_stock_picking_sale_order_link-9.0.1.0.0.dist-info/metadata.json
odoo9_addon_stock_picking_sale_order_link-9.0.1.0.0.dist-info/DESCRIPTION.rst
odoo9_addon_stock_picking_sale_order_link-9.0.1.0.0.dist-info/METADATA
odoo9_addon_stock_picking_sale_order_link-9.0.1.0.0.dist-info/namespace_packages.txt
odoo_addons/stock_picking_sale_order_link/__openerp__.py
odoo_addons/stock_picking_sale_order_link/__init__.py
odoo_addons/stock_picking_sale_order_link/README.rst
odoo_addons/stock_picking_sale_order_link/models/__init__.py
odoo_addons/stock_picking_sale_order_link/models/stock_picking.py
odoo_addons/stock_picking_sale_order_link/i18n/es.po
odoo_addons/stock_picking_sale_order_link/views/stock_picking_view.xml
odoo_addons/stock_picking_sale_order_link/tests/test_stock_picking_sale_order_link.py
odoo_addons/stock_picking_sale_order_link/tests/__init__.py
odoo_addons/stock_picking_sale_order_link/static/description/icon.png
